{
  "message": "Anime encontrado",
  "data": {
    "id": 1417,
    "nome": "Henjin no Salad Bowl",
    "link": "https://animefire.plus/animes/henjin-no-salad-bowl-todos-os-episodios",
    "texto_original": "Henjin no Salad Bowl",
    "rating": 7.27,
    "classificacao_etaria": "A14",
    "imagem_original": "https://animefire.plus/img/animes/henjin-no-salad-bowl.webp",
    "imagem_pasta": "https://animefire.plus/img/animes/henjin-no-salad-bowl/",
    "secao": "legendados",
    "pagina": 14,
    "total_episodios": 12,
    "link_video": "https://animefire.plus/video/henjin-no-salad-bowl"
  }
}
