{
  "message": "Anime encontrado",
  "data": {
    "id": 2788,
    "nome": "Nozomanu Fushi no Boukensha",
    "link": "https://animefire.plus/animes/nozomanu-fushi-no-boukensha-todos-os-episodios",
    "texto_original": "Nozomanu Fushi no Boukensha",
    "rating": 7.43,
    "classificacao_etaria": "A14",
    "imagem_original": "https://animefire.plus/img/animes/nozomanu-fushi-no-boukensha.webp",
    "imagem_pasta": "https://animefire.plus/img/animes/nozomanu-fushi-no-boukensha/",
    "secao": "legendados",
    "pagina": 18,
    "total_episodios": 12,
    "link_video": "https://animefire.plus/video/nozomanu-fushi-no-boukensha"
  }
}
