{
  "message": "Anime encontrado",
  "data": {
    "id": 3997,
    "nome": "Uchuu Patrol Luluco",
    "link": "https://animefire.plus/animes/uchuu-patrol-luluco-todos-os-episodios",
    "texto_original": "Uchuu Patrol Luluco",
    "rating": 7.66,
    "classificacao_etaria": "A14",
    "imagem_original": "https://animefire.plus/img/animes/uchuu-patrol-luluco.webp",
    "imagem_pasta": "https://animefire.plus/img/animes/uchuu-patrol-luluco/",
    "secao": "legendados",
    "pagina": 140,
    "total_episodios": 13,
    "link_video": "https://animefire.plus/video/uchuu-patrol-luluco"
  }
}
