{
  "message": "Anime encontrado",
  "data": {
    "id": 1153,
    "nome": "Gibiate",
    "link": "https://animefire.plus/animes/gibiate-todos-os-episodios",
    "texto_original": "Gibiate",
    "rating": null,
    "classificacao_etaria": "A16",
    "imagem_original": "https://animefire.plus/img/animes/gibiate.webp",
    "imagem_pasta": "https://animefire.plus/img/animes/gibiate/",
    "secao": "legendados",
    "pagina": 57,
    "total_episodios": 12,
    "link_video": "https://animefire.plus/video/gibiate"
  }
}
