{
  "message": "Anime encontrado",
  "data": {
    "id": 1701,
    "nome": "Izumo: Takeki Tsurugi no Senki",
    "link": "https://animefire.plus/animes/izumo-takeki-tsurugi-no-senki-todos-os-episodios",
    "texto_original": "Izumo: Takeki Tsurugi no Senki",
    "rating": 6.3,
    "classificacao_etaria": "A14",
    "imagem_original": "https://animefire.plus/img/animes/izumo-takeki-tsurugi-no-senki.webp",
    "imagem_pasta": "https://animefire.plus/img/animes/izumo-takeki-tsurugi-no-senki/",
    "secao": "legendados",
    "pagina": 160,
    "total_episodios": 12,
    "link_video": "https://animefire.plus/video/izumo-takeki-tsurugi-no-senki"
  }
}
