{
  "message": "Anime encontrado",
  "data": {
    "id": 1723,
    "nome": "Jigoku Shoujo (Dublado)",
    "link": "https://animefire.plus/animes/jigoku-shoujo-dublado-todos-os-episodios",
    "texto_original": "Jigoku Shoujo (Dublado)",
    "rating": 7.68,
    "classificacao_etaria": "A16",
    "imagem_original": "https://animefire.plus/img/animes/jigoku-shoujo.webp",
    "imagem_pasta": "https://animefire.plus/img/animes/jigoku-shoujo/",
    "secao": "dublados,legendados",
    "pagina": 25,
    "total_episodios": 26,
    "link_video": "https://animefire.plus/video/jigoku-shoujo-dublado"
  }
}
