{
  "message": "Anime encontrado",
  "data": {
    "id": 2655,
    "nome": "Nanatsu no Bitoku",
    "link": "https://animefire.plus/animes/nanatsu-no-bitoku-todos-os-episodios",
    "texto_original": "Nanatsu no Bitoku",
    "rating": 5.27,
    "classificacao_etaria": "A18",
    "imagem_original": "https://animefire.plus/img/animes/nanatsu-no-bitoku.webp",
    "imagem_pasta": "https://animefire.plus/img/animes/nanatsu-no-bitoku/",
    "secao": "legendados",
    "pagina": 146,
    "total_episodios": 7,
    "link_video": "https://animefire.plus/video/nanatsu-no-bitoku"
  }
}
