{
  "message": "Anime encontrado",
  "data": {
    "id": 466,
    "nome": "Boku no Tsuma wa Kanjou ga Nai",
    "link": "https://animefire.plus/animes/boku-no-tsuma-wa-kanjou-ga-nai-todos-os-episodios",
    "texto_original": "Boku no Tsuma wa Kanjou ga Nai",
    "rating": 6.75,
    "classificacao_etaria": "A14",
    "imagem_original": "https://animefire.plus/img/animes/boku-no-tsuma-wa-kanjou-ga-nai.webp",
    "imagem_pasta": "https://animefire.plus/img/animes/boku-no-tsuma-wa-kanjou-ga-nai/",
    "secao": "legendados",
    "pagina": 12,
    "total_episodios": 12,
    "link_video": "https://animefire.plus/video/boku-no-tsuma-wa-kanjou-ga-nai"
  }
}
