{
  "message": "10 animes aleatórios",
  "data": [
    {
      "id": 3716,
      "nome": "Taishou Yakyuu Musume.",
      "link": "https://animefire.plus/animes/taishou-yakyuu-musume-todos-os-episodios",
      "texto_original": "Taishou Yakyuu Musume.",
      "rating": 7.38,
      "classificacao_etaria": "A14",
      "imagem_original": "https://animefire.plus/img/animes/taishou-yakyuu-musume.webp",
      "imagem_pasta": "https://animefire.plus/img/animes/taishou-yakyuu-musume/",
      "secao": "legendados",
      "pagina": 146,
      "total_episodios": 12,
      "link_video": "https://animefire.plus/video/taishou-yakyuu-musume"
    },
    {
      "id": 1602,
      "nome": "Ikebukuro West Gate Park",
      "link": "https://animefire.plus/animes/ikebukuro-west-gate-park-todos-os-episodios",
      "texto_original": "Ikebukuro West Gate Park",
      "rating": null,
      "classificacao_etaria": "A14",
      "imagem_original": "https://animefire.plus/img/animes/ikebukuro-west-gate-park.webp",
      "imagem_pasta": "https://animefire.plus/img/animes/ikebukuro-west-gate-park/",
      "secao": "legendados",
      "pagina": 52,
      "total_episodios": 12,
      "link_video": "https://animefire.plus/video/ikebukuro-west-gate-park"
    },
    {
      "id": 1095,
      "nome": "Galaxy Angel Music Collection: Shouen to Shien no Cassoulet",
      "link": "https://animefire.plus/animes/galaxy-angel-music-collection-shouen-to-shien-no-cassoulet-todos-os-episodios",
      "texto_original": "Galaxy Angel Music Collection: Shouen to Shien no Cassoulet",
      "rating": 6.99,
      "classificacao_etaria": "A14",
      "imagem_original": "https://animefire.plus/img/animes/galaxy-angel-music-collection-shouen-to-shien-no-cassoulet.webp",
      "imagem_pasta": "https://animefire.plus/img/animes/galaxy-angel-music-collection-shouen-to-shien-no-cassoulet/",
      "secao": "legendados",
      "pagina": 84,
      "total_episodios": 1,
      "link_video": "https://animefire.plus/video/galaxy-angel-music-collection-shouen-to-shien-no-cassoulet"
    },
    {
      "id": 870,
      "nome": "Dr. Stone: Ryuusui (Dublado)",
      "link": "https://animefire.plus/animes/dr-stone-ryuusui-dublado-todos-os-episodios",
      "texto_original": "Dr. Stone: Ryuusui (Dublado)",
      "rating": 8.13,
      "classificacao_etaria": "A14",
      "imagem_original": "https://animefire.plus/img/animes/dr-stone-ryuusui.webp",
      "imagem_pasta": "https://animefire.plus/img/animes/dr-stone-ryuusui/",
      "secao": "dublados,legendados",
      "pagina": 9,
      "total_episodios": 1,
      "link_video": "https://animefire.plus/video/dr-stone-ryuusui-dublado"
    },
    {
      "id": 872,
      "nome": "Dr. Stone: Science Future Part 2",
      "link": "https://animefire.plus/animes/dr-stone-science-future-part-2-todos-os-episodios",
      "texto_original": "Dr. Stone: Science Future Part 2",
      "rating": 8.22,
      "classificacao_etaria": "A14",
      "imagem_original": "https://animefire.plus/img/animes/dr-stone-science-future-part-2.webp",
      "imagem_pasta": "https://animefire.plus/img/animes/dr-stone-science-future-part-2/",
      "secao": "legendados,lancamentos",
      "pagina": 1,
      "total_episodios": 4,
      "link_video": "https://animefire.plus/video/dr-stone-science-future-part-2"
    },
    {
      "id": 410,
      "nome": "Black Clover (Dublado)",
      "link": "https://animefire.plus/animes/black-clover-dublado-todos-os-episodios",
      "texto_original": "Black Clover (Dublado)",
      "rating": 7.27,
      "classificacao_etaria": "A14",
      "imagem_original": "https://animefire.plus/img/animes/black-clover.webp",
      "imagem_pasta": "https://animefire.plus/img/animes/black-clover/",
      "secao": "dublados,legendados",
      "pagina": 20,
      "total_episodios": 170,
      "link_video": "https://animefire.plus/video/black-clover-dublado"
    },
    {
      "id": 100,
      "nome": "Air Master",
      "link": "https://animefire.plus/animes/air-master-todos-os-episodios",
      "texto_original": "Air Master",
      "rating": 7.04,
      "classificacao_etaria": "A16",
      "imagem_original": "https://animefire.plus/img/animes/air-master.webp",
      "imagem_pasta": "https://animefire.plus/img/animes/air-master/",
      "secao": "legendados",
      "pagina": 59,
      "total_episodios": 26,
      "link_video": "https://animefire.plus/video/air-master"
    },
    {
      "id": 871,
      "nome": "Dr. Stone: Science Future (Dublado)",
      "link": "https://animefire.plus/animes/dr-stone-science-future-dublado-todos-os-episodios",
      "texto_original": "Dr. Stone: Science Future (Dublado)",
      "rating": 8.24,
      "classificacao_etaria": "A14",
      "imagem_original": "https://animefire.plus/img/animes/dr-stone-science-future.webp",
      "imagem_pasta": "https://animefire.plus/img/animes/dr-stone-science-future/",
      "secao": "dublados,legendados,lancamentos",
      "pagina": 1,
      "total_episodios": 12,
      "link_video": "https://animefire.plus/video/dr-stone-science-future-dublado"
    },
    {
      "id": 191,
      "nome": "Ansatsu Kyoushitsu 2nd Season (Dublado)",
      "link": "https://animefire.plus/animes/ansatsu-kyoushitsu-2nd-season-dublado-todos-os-episodios",
      "texto_original": "Ansatsu Kyoushitsu 2nd Season (Dublado)",
      "rating": 8.55,
      "classificacao_etaria": "A14",
      "imagem_original": "https://animefire.plus/img/animes/ansatsu-kyoushitsu-2nd-season.webp",
      "imagem_pasta": "https://animefire.plus/img/animes/ansatsu-kyoushitsu-2nd-season/",
      "secao": "dublados,legendados",
      "pagina": 19,
      "total_episodios": 23,
      "link_video": "https://animefire.plus/video/ansatsu-kyoushitsu-2nd-season-dublado"
    },
    {
      "id": 877,
      "nome": "Dragon Ball Heroes (Dublado)",
      "link": "https://animefire.plus/animes/dragon-ball-heroes-dublado-todos-os-episodios",
      "texto_original": "Dragon Ball Heroes (Dublado)",
      "rating": 5.62,
      "classificacao_etaria": "A14",
      "imagem_original": "https://animefire.plus/img/animes/dragon-ball-heroes.webp",
      "imagem_pasta": "https://animefire.plus/img/animes/dragon-ball-heroes/",
      "secao": "dublados,legendados,lancamentos",
      "pagina": 26,
      "total_episodios": 16,
      "link_video": "https://animefire.plus/video/dragon-ball-heroes-dublado"
    }
  ],
  "total": 10,
  "version": 2
}
