{
  "message": "Lista de episódios do anime: Tantei Opera Milky Holmes Dai 2 Maku",
  "anime": {
    "id": 3743,
    "nome": "Tantei Opera Milky Holmes Dai 2 Maku",
    "link": "https://animefire.plus/animes/tantei-opera-milky-holmes-dai-2-maku-todos-os-episodios",
    "link_video": "https://animefire.plus/video/tantei-opera-milky-holmes-dai-2-maku",
    "rating": "7.27",
    "classificacao_etaria": "A14"
  },
  "episodes": [
    {
      "episode_number": 1,
      "episode_url": "https://animefire.plus/video/tantei-opera-milky-holmes-dai-2-maku/1",
      "anime_id": 3743,
      "anime_name": "Tantei Opera Milky Holmes Dai 2 Maku"
    },
    {
      "episode_number": 2,
      "episode_url": "https://animefire.plus/video/tantei-opera-milky-holmes-dai-2-maku/2",
      "anime_id": 3743,
      "anime_name": "Tantei Opera Milky Holmes Dai 2 Maku"
    },
    {
      "episode_number": 3,
      "episode_url": "https://animefire.plus/video/tantei-opera-milky-holmes-dai-2-maku/3",
      "anime_id": 3743,
      "anime_name": "Tantei Opera Milky Holmes Dai 2 Maku"
    },
    {
      "episode_number": 4,
      "episode_url": "https://animefire.plus/video/tantei-opera-milky-holmes-dai-2-maku/4",
      "anime_id": 3743,
      "anime_name": "Tantei Opera Milky Holmes Dai 2 Maku"
    },
    {
      "episode_number": 5,
      "episode_url": "https://animefire.plus/video/tantei-opera-milky-holmes-dai-2-maku/5",
      "anime_id": 3743,
      "anime_name": "Tantei Opera Milky Holmes Dai 2 Maku"
    },
    {
      "episode_number": 6,
      "episode_url": "https://animefire.plus/video/tantei-opera-milky-holmes-dai-2-maku/6",
      "anime_id": 3743,
      "anime_name": "Tantei Opera Milky Holmes Dai 2 Maku"
    },
    {
      "episode_number": 7,
      "episode_url": "https://animefire.plus/video/tantei-opera-milky-holmes-dai-2-maku/7",
      "anime_id": 3743,
      "anime_name": "Tantei Opera Milky Holmes Dai 2 Maku"
    },
    {
      "episode_number": 8,
      "episode_url": "https://animefire.plus/video/tantei-opera-milky-holmes-dai-2-maku/8",
      "anime_id": 3743,
      "anime_name": "Tantei Opera Milky Holmes Dai 2 Maku"
    },
    {
      "episode_number": 9,
      "episode_url": "https://animefire.plus/video/tantei-opera-milky-holmes-dai-2-maku/9",
      "anime_id": 3743,
      "anime_name": "Tantei Opera Milky Holmes Dai 2 Maku"
    }
  ],
  "total_episodes": 9
}